calculator_package_GUSAEZG/__init__.py
calculator_package_GUSAEZG/calculator.py
calculator_package_gusaezg-0.0.2.dist-info/METADATA
calculator_package_gusaezg-0.0.2.dist-info/WHEEL
calculator_package_gusaezg-0.0.2.dist-info/licenses/LICENSE
calculator_package_gusaezg-0.0.2.dist-info/RECORD
