Metadata-Version: 2.1
Name: calculator_package_GUSAEZG
Version: 0.0.2
Project-URL: Homepage, https://github.com/TuringCollegeSubmissions/gusaezg-DWWP.1
Project-URL: Bug Tracker, https://github.com/TuringCollegeSubmissions/gusaezg-DWWP.1/issues
Author-email: Guillermo Sáez Gómez <guillermosaezgomez@gmail.com>
License-File: LICENSE
Classifier: License :: OSI Approved :: MIT License
Classifier: Operating System :: OS Independent
Classifier: Programming Language :: Python :: 3
Requires-Python: >=3.7
